<annotation>
	<folder>images_1</folder>
	<filename>t (149).jpg</filename>
	<path>D:\labelimg_dataset\images_1\t (149).jpg</path>
	<source>
		<database>Unknown</database>
	</source>
	<size>
		<width>339</width>
		<height>240</height>
		<depth>3</depth>
	</size>
	<segmented>0</segmented>
	<object>
		<name>car</name>
		<pose>Unspecified</pose>
		<truncated>0</truncated>
		<difficult>0</difficult>
		<bndbox>
			<xmin>12</xmin>
			<ymin>24</ymin>
			<xmax>327</xmax>
			<ymax>210</ymax>
		</bndbox>
	</object>
</annotation>
