<annotation>
	<folder>images_1</folder>
	<filename>t (218).jpg</filename>
	<path>D:\labelimg_dataset\images_1\t (218).jpg</path>
	<source>
		<database>Unknown</database>
	</source>
	<size>
		<width>365</width>
		<height>243</height>
		<depth>3</depth>
	</size>
	<segmented>0</segmented>
	<object>
		<name>man</name>
		<pose>Unspecified</pose>
		<truncated>0</truncated>
		<difficult>0</difficult>
		<bndbox>
			<xmin>42</xmin>
			<ymin>6</ymin>
			<xmax>219</xmax>
			<ymax>184</ymax>
		</bndbox>
	</object>
</annotation>
