<annotation>
	<folder>images_1</folder>
	<filename>t (39).jpg</filename>
	<path>D:\labelimg_dataset\images_1\t (39).jpg</path>
	<source>
		<database>Unknown</database>
	</source>
	<size>
		<width>115</width>
		<height>117</height>
		<depth>3</depth>
	</size>
	<segmented>0</segmented>
	<object>
		<name>truck</name>
		<pose>Unspecified</pose>
		<truncated>1</truncated>
		<difficult>0</difficult>
		<bndbox>
			<xmin>3</xmin>
			<ymin>2</ymin>
			<xmax>115</xmax>
			<ymax>105</ymax>
		</bndbox>
	</object>
</annotation>
